odoo/addons/l10n_ch_pain_credit_transfer/README.rst
odoo/addons/l10n_ch_pain_credit_transfer/__init__.py
odoo/addons/l10n_ch_pain_credit_transfer/__manifest__.py
odoo/addons/l10n_ch_pain_credit_transfer/data/pain.001.001.03.ch.02.xsd
odoo/addons/l10n_ch_pain_credit_transfer/i18n/de.po
odoo/addons/l10n_ch_pain_credit_transfer/i18n/fr.po
odoo/addons/l10n_ch_pain_credit_transfer/i18n/l10n_ch_pain_credit_transfer.pot
odoo/addons/l10n_ch_pain_credit_transfer/models/__init__.py
odoo/addons/l10n_ch_pain_credit_transfer/models/account_payment_method.py
odoo/addons/l10n_ch_pain_credit_transfer/readme/CONFIGURE.rst
odoo/addons/l10n_ch_pain_credit_transfer/readme/CONTRIBUTORS.rst
odoo/addons/l10n_ch_pain_credit_transfer/readme/DESCRIPTION.rst
odoo/addons/l10n_ch_pain_credit_transfer/readme/USAGE.rst
odoo/addons/l10n_ch_pain_credit_transfer/static/description/icon.png
odoo/addons/l10n_ch_pain_credit_transfer/static/description/index.html
odoo/addons/l10n_ch_pain_credit_transfer/tests/__init__.py
odoo/addons/l10n_ch_pain_credit_transfer/tests/test_ch_sct.py
odoo14_addon_l10n_ch_pain_credit_transfer-14.0.1.0.1.dev2.dist-info/METADATA
odoo14_addon_l10n_ch_pain_credit_transfer-14.0.1.0.1.dev2.dist-info/WHEEL
odoo14_addon_l10n_ch_pain_credit_transfer-14.0.1.0.1.dev2.dist-info/top_level.txt
odoo14_addon_l10n_ch_pain_credit_transfer-14.0.1.0.1.dev2.dist-info/RECORD
